{
  "project_info": {
    "project_number": "1054673633326",
    "project_id": "plugin-11087",
    "storage_bucket": "plugin-11087.appspot.com"
  },
  "client": [
    {
      "client_info": {
        "mobilesdk_app_id": "1:1054673633326:android:de8dec2fd1c4f535dcdfbf",
        "android_client_info": {
          "package_name": "com.android.tai"
        }
      },
      "oauth_client": [],
      "api_key": [
        {
          "current_key": "AIzaSyDoj57FQBvxjd5d6QPJ9IElKT7XyOFG9jE"
        }
      ],
      "services": {
        "appinvite_service": {
          "other_platform_oauth_client": []
        }
      }
    }
  ],
  "configuration_version": "1"
}